{
  "format_version": "1.12",
  "minecraft:recipe_shaped": {
    "description": {
    "identifier": "morefood:bottled_red_wine"
    },
    "tags": [ "crafting_table" ],
    "pattern": [
      "H H",
      "UBY",
      "W#W"
    ],
    "key": {
      "#": {
        "item": "minecraft:bucket",
        "data": 8
      },
      "H": {
        "item": "morefood:raspberry"
      },
      "W": {
        "item": "morefood:strawberry"
      },
      "B": {
        "item": "morefood:bottle"
      },
      "Y": {
        "item": "morefood:yeast"
      },
      "U": {
        "item": "minecraft:sugar"
      }
    },
    "result": [
      {"item": "morefood:bottled_red_wine"},
      {"item": "minecraft:bucket", "data": 0}
    ]
  }
}