{
  "credit": "Thanks to Legopitstop for creating this useful resource. https://legopitstop.weebly.com/media.html",
  "format_version": "1.16.1",
  "minecraft:recipe_shaped": {
    "description": {
    "identifier": "morefood:orange_jelly"
    },
    "tags": [ "crafting_table" ],
    "pattern": [
      "#PX",
      "#YZ"
    ],
    "key": {
      "#": {
        "item": "morefood:orange"
      },
      "P": {
        "item": "morefood:gelatin"
      },
      "X": {
        "item": "minecraft:ice"
      },
      "Y": {
        "item": "minecraft:bowl"
      },
      "Z": {
        "item": "minecraft:bucket",
        "data": 8
      }
    },
    "result": [
      {
        "item": "morefood:orange_jelly"
      },
      {
        "item": "minecraft:bucket",
        "data": 0
      }
    ]
  }
}