{
    "format_version": "1.17.1",
    "minecraft:recipe_shaped": {
        "description": {
            "identifier": "morefood:vanilla_seed_sack"
        },
        "tags": [
            "crafting_table"
        ],
        "pattern": [
            "###",
            "###",
            "###"
        ],
        "key": {
            "#": {
                "item": "morefood:vanilla_seeds"
            }
        },
        "result": [
            {
                "item": "morefood:vanilla_seed_sack",
                "count": 1
            }
        ]
    }
}