{
    "format_version": "1.17.1",
    "minecraft:recipe_shaped": {
        "description": {
            "identifier": "morefood:icecrush_apple_raspberry"
        },
        "tags": [
            "crafting_table"
        ],
        "group": "morefood:icecrush",
        "pattern": [
            "#Y#",
            " P ",
            " X "
        ],
        "key": {
            "#": {
                "item": "morefood:raspberry"
            },
            "P": {
                "item": "morefood:empty_icecrush_glass"
            },
            "X": {
                "item": "minecraft:ice"
            },
            "Y": {
                "item": "minecraft:apple"
            }
        },
        "result": [
            {
                "item": "morefood:icecrush_apple_raspberry"
            }
        ]
    }
}