{
    "format_version": "1.20.30",
    "minecraft:recipe_shaped": {
        "description": {
            "identifier": "morefood:ramen_noodles"
        },
        "tags": [
            "crafting_table"
        ],
        "pattern": [
            "# X",
            "YZA"
        ],
        "key": {
            "#": {
                "item": "morefood:corn"
            },
            "X": {
                "item": "morefood:noodles"
            },
            "Y": {
                "item": "minecraft:egg"
            },
            "Z": {
                "item": "morefood:large_bowl"
            },
            "A": {
                "item": "minecraft:cooked_chicken"
            }
        },
        "result": {
            "item": "morefood:ramen_noodles"
        },
        "unlock": [
            {
                "item": "morefood:corn"
            },
            {
                "item": "morefood:noodles"
            },
            {
                "item": "minecraft:egg"
            },
            {
                "item": "morefood:large_bowl"
            },
            {
                "item": "minecraft:cooked_chicken"
            }
        ]
    }
}