{
    "language.version": "??",
    "language.code": "zh_cn",
    "language.name": "Chinese",
    "language.translator": "Gouzei",
    "upd.ch": "changelog",
    "upd.version": " §ev1.1.5 - pre1",
    "changelog.0": "͸+ 增加了胡椒丛材质",
    "changelog.1": "͸+ ​固定MF010",
    "changelog.2": "͸+ 增加了创意饥饿物品 (创意单品)",
    "changelog.3": "͸+ 增加了万圣节内容",
    "changelog.4": "͸+ 将测试功能设置更改为假日功能",
    "changelog.5": "͸+ 小树苗会长成大树",
    "tile.morefood:block_apple.name": "苹果块",
    "tile.morefood:block_banana.name": "香蕉块",
    "tile.morefood:block_golden_apple.name": "金苹果块",
    "tile.morefood:block_grape.name": "葡萄块",
    "tile.morefood:block_hops.name": "啤酒花块",
    "tile.morefood:block_lemon.name": "柠檬块",
    "tile.morefood:block_olives.name": "橄榄块",
    "tile.morefood:block_orange.name": "橙子块",
    "tile.morefood:block_plum.name": "李子块",
    "tile.morefood:block_raspberry.name": "树莓块",
    "tile.morefood:block_strawberry.name": "草莓块",
    "tile.morefood:block_baked_potato.name": "烤土豆块",
    "tile.morefood:block_carrots.name": "胡萝卜块",
    "tile.morefood:block_potato.name": "马铃薯块",
    "tile.morefood:block_cookie.name": "饼干块",
    "tile.morefood:block_dark_chocolate.name": "黑巧克力块",
    "tile.morefood:block_milk_chocolate.name": "牛奶巧克力块",
    "tile.morefood:block_white_chocolate.name": "白巧克力块",
    "tile.morefood:block_cooked_beef.name": "熟牛肉块",
    "tile.morefood:block_cooked_chicken.name": "熟鸡肉块",
    "tile.morefood:block_cooked_mutton.name": "熟羊肉块",
    "tile.morefood:block_cooked_rabbit.name": "熟兔肉快",
    "tile.morefood:block_cooked_squid.name": "熟鱿鱼块",
    "tile.morefood:block_raw_beef.name": "生牛肉块",
    "tile.morefood:block_raw_chicken.name": "生鸡肉块",
    "tile.morefood:block_raw_mutton.name": "生羊肉块",
    "tile.morefood:block_raw_rabbit.name": "生兔肉块",
    "tile.morefood:block_raw_squid.name": "生鱿鱼块",
    "tile.morefood:apple_leaves.name": "苹果树叶",
    "tile.morefood:banana_leaves.name": "香蕉树叶",
    "tile.morefood:coconut_leaves.name": "椰子树叶",
    "tile.morefood:lemon_leaves.name": "柠檬树叶",
    "tile.morefood:olive_leaves.name": "橄榄树叶",
    "tile.morefood:orange_leaves.name": "橙子树叶",
    "tile.morefood:plum_leaves.name": "李子树叶",
    "item.morefood:creative_hunger": "创意饥饿 §4",
    "item.morefood:cooked_chicken_piece": "熟鸡肉片",
    "item.morefood:cooked_wedges": "熟楔子",
    "item.morefood:pepper": "胡椒",
    "item.morefood:sparkling_water_bottle": "汽水瓶",
    "item.morefood:chicken_nugget": "鸡块",
    "item.morefood:cooked_chicken_nugget": "熟鸡块",
    "item.morefood:netherite_apple": "下界合金苹果",
    "item.morefood:cooked_hoglin_meat": "熟疣猪兽肉",
    "item.morefood:hoglin_meat": "疣猪兽肉",
    "item.morefood:fungus_stew": "木耳炖",
    "item.morefood:nether_cookie": "下界合金饼干",
    "item.morefood:netherwart_chicken_soup": "地狱疣鸡汤",
    "item.morefood:netherwart_mushroom_soup": "地狱疣蘑菇汤",
    "item.morefood:shroomlight_slices": "小型切片",
    "item.morefood:warped_berries": "扭曲浆果",
    "item.morefood:wart_pie": "疣派",
    "item.morefood:rotten_porkchop": "腐烂的猪排",
    "item.morefood:redwhiteblue_cake": "红白蓝蛋糕",
    "item.morefood:rainbow_cake": "彩虹蛋糕",
    "item.morefood:chocolate_cake": "巧克力蛋糕( # More Food )",
    "item.morefood:ketchup": "番茄酱",
    "item.morefood:spaghetti": "意大利面",
    "item.morefood:sashimi": "生鱼片",
    "item.morefood:onigiri": "饭团",
    "item.morefood:americano": "美国菜",
    "item.morefood:bacon": "培根",
    "item.morefood:bacon_egg_muffin": "培根蛋松饼",
    "item.morefood:bacon_egg_sandwich": "培根鸡蛋三明治",
    "item.morefood:bat_meat": "蝙蝠肉",
    "item.morefood:beef_sub": "牛肉饼",
    "item.morefood:blue_cupcake": "蓝色纸杯蛋糕",
    "item.morefood:bread_loaf": "面包条",
    "item.morefood:breakfast_sub": "早餐面包",
    "item.morefood:burger_bun": "汉堡包",
    "item.morefood:burrito": "玉米煎饼",
    "item.morefood:butter": "黄油",
    "item.morefood:cappuccino": "卡布奇诺",
    "item.morefood:cereal": "谷类食品",
    "item.morefood:cheese_bucket": "奶酪桶",
    "item.morefood:cheese_toastie": "奶酪吐司",
    "item.morefood:cheese_wedge": "奶酪楔",
    "item.morefood:chicken_fajita": "鸡肉卷饼",
    "item.morefood:chicken_select": "精选鸡肉",
    "item.morefood:chicken_sub": "鸡肉面包",
    "item.morefood:coconut_meat": "椰子肉",
    "item.morefood:coconut_milk": "椰奶",
    "item.morefood:cooked_bacon": "熟培根",
    "item.morefood:cooked_bat_meat": "熟蝙蝠肉",
    "item.morefood:cooked_hotdog_sausage": "熟热狗香肠",
    "item.morefood:cooked_sausage": "香肠",
    "item.morefood:cornflour": "玉米粉",
    "item.morefood:custard": "奶油冻",
    "item.morefood:cut_bread": "面包切片",
    "item.morefood:cut_fries": "薯条切片",
    "item.morefood:dark_chocolate": "黑巧克力",
    "item.morefood:dough": "面团",
    "item.morefood:flour": "面粉",
    "item.morefood:fried_egg": "煎蛋",
    "item.morefood:fried_squid": "炸鱿鱼",
    "item.morefood:fries": "薯条",
    "item.morefood:gelatin": "明胶",
    "item.morefood:hamburger": "汉堡",
    "item.morefood:hamburger_patty": "汉堡肉饼",
    "item.morefood:hops": "啤酒花",
    "item.morefood:hot_cocoa": "热可可",
    "item.morefood:hot_coffee": "热咖啡",
    "item.morefood:hot_tea": "热茶",
    "item.morefood:hotdog": "热狗",
    "item.morefood:hotdog_bun": "热狗面包",
    "item.morefood:hotdog_sausage": "热狗香肠",
    "item.morefood:jam": "果酱",
    "item.morefood:jelly_sandwich": "果酱三明治",
    "item.morefood:kebab": "烤肉串",
    "item.morefood:macchiato": "玛奇朵咖啡",
    "item.morefood:milk_carton": "牛奶盒",
    "item.morefood:milk_chocolate": "牛奶巧克力",
    "item.morefood:mocha": "摩卡咖啡",
    "item.morefood:muffin_bun": "松饼面包",
    "item.morefood:noodles": "面条",
    "item.morefood:oil": "食用油",
    "item.morefood:orange_jelly": "橙子酱",
    "item.morefood:pancakes": "煎饼",
    "item.morefood:pasta": "意大利面食",
    "item.morefood:pink_cupcake": "粉色纸杯蛋糕",
    "item.morefood:pitta_bread": "批塔饼",
    "item.morefood:pizza": "披萨",
    "item.morefood:pizza_base": "披萨底料",
    "item.morefood:pizza_slice": "披萨片",
    "item.morefood:popcorn": "爆米花",
    "item.morefood:popcorn_bucket": "爆米花桶",
    "item.morefood:ramen_noodles": "拉面",
    "item.morefood:raw_hamburger_patty": "生汉堡肉饼",
    "item.morefood:raw_sausage": "生香肠",
    "item.morefood:raw_squid": "生鱿鱼",
    "item.morefood:raw_veganburger_patty": "生素汉堡肉饼",
    "item.morefood:raw_wedges": "生楔子",
    "item.morefood:rice": "米饭",
    "item.morefood:rice_pudding": "米饭布丁",
    "item.morefood:round_cheese": "圆形奶酪",
    "item.morefood:salt": "盐",
    "item.morefood:sausage_egg_muffin": "香肠蛋松饼",
    "item.morefood:sausage_egg_sandwich": "香肠鸡蛋三明治",
    "item.morefood:sparkling_water_bucket": "汽水桶",
    "item.morefood:strawberry_jelly": "草莓酱",
    "item.morefood:sub_bun": "小面包",
    "item.morefood:sushi": "寿司",
    "item.morefood:taco": "玉米卷",
    "item.morefood:tea_leaves": "茶叶",
    "item.morefood:toast": "烤面包",
    "item.morefood:toffee": "太妃糖",
    "item.morefood:toffee_latte": "太妃糖拿铁",
    "item.morefood:tomato_puree": "番茄泥",
    "item.morefood:tortilla": "玉米饼",
    "item.morefood:turkish_delight": "土耳其软糖",
    "item.morefood:vanilla_extract": "香草精",
    "item.morefood:vanilla_latte": "香草拿铁",
    "item.morefood:vanilla_pod": "香草豆荚",
    "item.morefood:veganburger": "蔬菜汉堡",
    "item.morefood:veganburger_patty": "蔬菜汉堡肉饼",
    "item.morefood:waffle": "华夫饼",
    "item.morefood:wedges_pot": "楔形锅",
    "item.morefood:white_chocolate": "白巧克力",
    "item.morefood:yeast": "酵母",
    "item.morefood:beer": "啤酒",
    "item.morefood:cider": "苹果酒",
    "item.morefood:red_wine": "红葡萄酒",
    "item.morefood:white_wine": "白葡萄酒",
    "item.morefood:bottled_beer": "啤酒瓶 100％",
    "item.morefood:bottled_cider": "苹果酒瓶 100％",
    "item.morefood:bottled_red_wine": "红葡萄酒瓶 100％",
    "item.morefood:bottled_white_wine": "白葡萄酒瓶 100％",
    "item.morefood:bottled_beer_75": "啤酒瓶 75％",
    "item.morefood:bottled_cider_75": "苹果酒瓶 75％",
    "item.morefood:bottled_red_wine_75": "红葡萄酒瓶 75％",
    "item.morefood:bottled_white_wine_75": "白葡萄酒瓶 75％",
    "item.morefood:bottled_beer_50": "啤酒瓶 50％",
    "item.morefood:bottled_cider_50": "苹果酒瓶 50％",
    "item.morefood:bottled_red_wine_50": "红葡萄酒瓶 50％",
    "item.morefood:bottled_white_wine_50": "白葡萄酒瓶 50％",
    "item.morefood:bottled_beer_25": "啤酒瓶 25％",
    "item.morefood:bottled_cider_25": "苹果酒瓶 25％",
    "item.morefood:bottled_red_wine_25": "红葡萄酒瓶 25％",
    "item.morefood:bottled_white_wine_25": "白葡萄酒瓶 25％",
    "item.morefood:bottled_beer_0": "啤酒瓶 0％",
    "item.morefood:bottled_cider_0": "苹果酒瓶 0％",
    "item.morefood:bottled_red_wine_0": "红葡萄酒瓶 0％",
    "item.morefood:bottled_white_wine_0": "白葡萄酒瓶 0％",
    "item.morefood:donut_chocolate": "巧克力甜甜圈",
    "item.morefood:donut_coffee": "咖啡甜甜圈",
    "item.morefood:donut_golden": "金色甜甜圈",
    "item.morefood:donut_iced": "冰甜甜圈",
    "item.morefood:donut_pink_ice": "粉红色冰甜甜圈",
    "item.morefood:donut_plain": "普通甜甜圈",
    "item.morefood:donut_strawberry": "草莓甜甜圈",
    "item.morefood:donut_toffee": "太妃糖甜甜圈",
    "item.morefood:banana": "香蕉",
    "item.morefood:grape": "葡萄",
    "item.morefood:lemon": "柠檬",
    "item.morefood:olives": "橄榄",
    "item.morefood:orange": "橙子",
    "item.morefood:plum": "李子",
    "item.morefood:raspberry": "树莓",
    "item.morefood:strawberry": "草莓",
    "item.morefood:tomato": "番茄",
    "item.morefood:ice_bowl": "冰淇淋碗",
    "item.morefood:icecream_banana": "香蕉冰淇淋",
    "item.morefood:icecream_chocolate": "巧克力冰淇淋",
    "item.morefood:icecream_cone": "蛋卷冰淇淋",
    "item.morefood:icecream_strawberry": "草莓冰淇淋",
    "item.morefood:icecream_toffee": "太妃糖冰淇淋",
    "item.morefood:icecream_vanilla": "香草冰淇淋",
    "item.morefood:icecrush_apple": "苹果碎冰",
    "item.morefood:icecrush_apple_raspberry": "苹果树莓碎冰",
    "item.morefood:icecrush_icecrush_berry": "浆果冰淇淋",
    "item.morefood:icecrush_berry": "浆果碎冰",
    "item.morefood:icecrush_grape": "葡萄碎冰",
    "item.morefood:icecrush_lemon": "柠檬碎冰",
    "item.morefood:icecrush_melon": "甜瓜碎冰",
    "item.morefood:icecrush_mixed_fruit": "混合水果碎冰",
    "item.morefood:icecrush_orange": "橙子碎冰",
    "item.morefood:icecrush_strawberry": "草莓碎冰",
    "item.morefood:juice_apple": "苹果汁",
    "item.morefood:juice_berry": "浆果汁",
    "item.morefood:juice_grape": "葡萄汁",
    "item.morefood:juice_lemon": "柠檬汁",
    "item.morefood:juice_melon": "甜瓜汁",
    "item.morefood:juice_mixed_fruit": "混合果汁",
    "item.morefood:juice_orange": "橙汁",
    "item.morefood:juice_strawberry": "草莓汁",
    "item.morefood:juice_tomato": "番茄汁",
    "item.morefood:milkshake_banana": "香蕉奶昔",
    "item.morefood:milkshake_chocolate": "巧克力奶昔",
    "item.morefood:milkshake_strawberry": "草莓奶昔",
    "item.morefood:pie_apple": "苹果派",
    "item.morefood:pie_apple_raspberry": "苹果树莓派",
    "item.morefood:pie_base": "派底料",
    "item.morefood:pie_berry": "浆果派",
    "item.morefood:pie_cheese": "奶酪派",
    "item.morefood:pie_chicken": "鸡肉馅饼",
    "item.morefood:pie_chocolate": "巧克力派",
    "item.morefood:pie_golden_apple": "金苹果派",
    "item.morefood:pie_lemon": "柠檬派",
    "item.morefood:pie_plum": "李子派",
    "item.morefood:pie_pork": "猪肉馅饼",
    "item.morefood:pie_steak": "牛肉馅饼",
    "item.morefood:pie_strawberry": "草莓派",
    "item.morefood:pie_toffee": "太妃糖派",
    "item.morefood:smoothie_banana": "香蕉冰沙",
    "item.morefood:smoothie_berry": "浆果冰沙",
    "item.morefood:smoothie_grape": "葡萄冰沙",
    "item.morefood:smoothie_mixed_fruit": "混合水果冰沙",
    "item.morefood:smoothie_raspberry": "树莓冰沙",
    "item.morefood:smoothie_strawberry": "草莓冰沙",
    "item.morefood:soda_apple": "苹果汽水",
    "item.morefood:soda_berry": "浆果汽水",
    "item.morefood:soda_grape": "葡萄汽水",
    "item.morefood:soda_lemon": "柠檬汽水",
    "item.morefood:soda_orange": "橙子汽水",
    "item.morefood:soda_strawberry": "草莓汽水",
    "item.morefood:corn_on_cob": "玉米棒子",
    "item.morefood:gherkin": "小黄瓜",
    "item.morefood:lettuce": "莴苣",
    "item.morefood:onion": "洋葱",
    "item.morefood:pickles": "泡菜",
    "item.morefood:sub_wrapper": "包装纸",
    "item.morefood:beer_glass": "啤酒杯",
    "item.morefood:beverage_cup": "饮料杯",
    "item.morefood:bottle": "瓶子",
    "item.morefood:carton": "纸箱",
    "item.morefood:chicken_select_box": "鸡肉选盒",
    "item.morefood:cream_carton": "奶油纸盒",
    "item.morefood:empty_icecrush_glass": "空冰淇淋杯",
    "item.morefood:empty_popcorn_bucket": "空爆米花桶",
    "item.morefood:empty_tumbler_glass": "空玻璃杯",
    "item.morefood:empty_wedges_pot": "空楔锅",
    "item.morefood:fry_wrapper": "油炸包装纸",
    "item.morefood:hot_beverage_cup": "热饮杯",
    "item.morefood:icing": "糖霜",
    "item.morefood:jar": "罐子",
    "item.morefood:pizza_box_opened": "打开的披萨盒",
    "item.morefood:recipe_book": "食谱",
    "item.morefood:soda_can_empty": "空的汽水罐",
    "item.morefood:starch": "淀粉",
    "item.morefood:wine_glass": "酒杯",
    "item.morefood:coconut": "椰子",
    "item.morefood:apple_sapling": "苹果树苗",
    "item.morefood:banana_sapling": "香蕉树苗",
    "item.morefood:lemon_sapling": "柠檬树苗",
    "item.morefood:olive_sapling": "橄榄树苗",
    "item.morefood:orange_sapling": "橙子树苗",
    "item.morefood:plum_sapling": "李子树苗",
    "item.morefood:coconut_sapling": "椰子树苗",
    "item.morefood:coffee_beans": "咖啡豆",
    "item.morefood:corn": "玉米",
    "item.morefood:barley_seeds": "大麦种子",
    "item.morefood:gherkin_seeds": "小黄瓜种子",
    "item.morefood:grape_seeds": "葡萄种子",
    "item.morefood:hops_seeds": "啤酒花种子",
    "item.morefood:lettuce_seeds": "莴苣种子",
    "item.morefood:onion_seeds": "洋葱种子",
    "item.morefood:raspberry_seeds": "树莓种子",
    "item.morefood:rice_seeds": "水稻种子",
    "item.morefood:strawberry_seeds": "草莓种子",
    "item.morefood:tea_seeds": "茶种子",
    "item.morefood:tomato_seeds": "番茄种子",
    "item.morefood:vanilla_seeds": "香草籽",
    "item.morefood:pepper_seeds": "胡椒籽",
    "item.morefood:knife_netherite": "下节合金刀",
    "item.morefood:knife_diamond": "钻石刀",
    "item.morefood:knife_golden": "金刀",
    "item.morefood:knife_iron": "铁刀",
    "item.morefood:knife_stone": "石刀",
    "item.morefood:knife_wooden": "木刀",
    "item.morefood:knife_emerald": "绿宝石刀",
    "item.morefood:wooden_spoon": "木勺",
    "howtoplay.category.morefood": "Morefood Addon更多食物行为包",
    "howtoplay.linkmf": "官方链接",
    "howtoplay.linkmf.title": "Morefood更多食物 : 官方链接",
    "howtoplay.linkmf.text.1": "官方下载:",
    "howtoplay.linkmf.text.2": "https://legopitstop.weebly.com/getmore.html",
    "howtoplay.linkmf.text.3": "发现了bug?填好bug表: https://legopitstop.weebly.com/bug-report-more-food.html",
    "howtoplay.linkmf.text.4": "想手工制作吗？查看配方页面:https://legopitstop.weebly.com/recipes-morefood.html",
    "howtoplay.linkmf.text.5": "看看更多的美食视频!并提交",
    "howtoplay.linkmf.text.6": "在这里找到官方百科: https://legopitstop.weebly.com/wiki-morefood.html",
    "howtoplay.linkmf.text.7": "或者这里: https://minecraft.gamepedia.com/User:Legopitstop/More_Food_Pack",
    "howtoplay.generalmf": "基本信息",
    "howtoplay.generalmf.title": "Morefood更多食物 : 基本信息",
    "howtoplay.generalmf.text.1": "想过Minecraft需要更多的食物吗?那这就是你想要的行为包!这个行为包增加了50多种食物。用来补充那些健康和饥饿点。这行为包还包括更多的植物来获得食物",
    "howtoplay.generalmf.header.1": "header 1",
    "howtoplay.generalmf.text.2": "text 2",
    "howtoplay.generalmf.text.3": "text 3",
    "howtoplay.generalmf.text.4": "text 4",
    "howtoplay.generalmf.header.2": "header 2",
    "howtoplay.generalmf.text.5": "text 5",
    "howtoplay.generalmf.text.6": "text 6",
    "howtoplay.generalmf.header.3": "header 3",
    "howtoplay.generalmf.text.7": "text 7",
    "howtoplay.mffaq": "常见问题解答",
    "howtoplay.mffaq.title": "Morefood更多食物 : 常见问题解答",
    "howtoplay.mffaq.text.1": "想要提问问题吗？去我的Discord在#faq频道，邀请链接:https://discord.io/Legopitstop",
    "howtoplay.mffaq.header.1": "MORE FOOD更多食物 故障排除:",
    "howtoplay.mffaq.text.2": "Bedrock/PE/Windows 10:",
    "howtoplay.mffaq.text.3": "-你开启实验了吗?",
    "howtoplay.mffaq.text.4": "-你是否在世界上安装了材质包和行为包?",
    "howtoplay.mffaq.text.5": "还是没帮上忙? 尝试联系legopitstop的Discord(链接以上) Discord标签: Legopitstop#4774",
    "howtoplay.mffaq.header.2": "定制工艺表在哪里?",
    "howtoplay.mffaq.text.6": "对基岩版本的行为包他们是没有自定义的工艺表,只是使用一个常规的工艺表。",
    "howtoplay.mffaq.header.3": "如何激活行为包测试？",
    "howtoplay.mffaq.text.7": "行为包测试只适用于Windows 10(在Windows 10上进行了测试),请按照以下步骤操作:",
    "howtoplay.mffaq.text.8": "打开行为包测试可盘种子和更多!",
    "howtoplay.mffaq.text.9": "1. 去查看行为包",
    "howtoplay.mffaq.text.10": "2. 选择打包”并单击“齿轮/设置",
    "howtoplay.mffaq.text.11": "3. 向左滑动滑块直到显示“正在测试”",
    "howtoplay.mffaq.text.12": "4. 对资源包做同样的操作。",
    "howtoplay.mffaq.header.4": "食谱在哪里？",
    "howtoplay.mffaq.text.13": "Minecraft基岩不支持食谱书中的自定义项目,有计划添加自定义食谱书，但是那会花费很多时间,我现在没有时间在谷歌文档中查找食谱。",
    "howtoplay.mffaq.header.5": "为什么食物不在背包里?",
    "howtoplay.mffaq.text.14": "Minecraft基岩不支持背包中的自定义项目。您可以使用/function命令轻松获取Creative中的物品。推翻这个错误:https://bugs.mojang.com/browse/MCPE-64487",
    "howtoplay.foodmf": "特色食物",
    "howtoplay.foodmf.title": "Morefood更多食物 : 特色食物",
    "howtoplay.foodmf.text.1": "有些食物有药水效果。下面是一些具有这些效果的食物",
    "howtoplay.foodmf.header.1": "药水效果",
    "howtoplay.foodmf.text.2": "啤酒",
    "howtoplay.foodmf.text.3": "  1/2:shank:",
    "howtoplay.foodmf.text.4": "  效率 III 00:20",
    "howtoplay.foodmf.text.5": "  反胃 II 00:15",
    "howtoplay.foodmf.text.6": "  失明 III 00:15",
    "howtoplay.foodmf.text.7": "果汁",
    "howtoplay.foodmf.text.8": "  1/2:shank:",
    "howtoplay.foodmf.text.9": "  效率 III 00:20",
    "howtoplay.foodmf.text.10": "  反胃 II 00:15",
    "howtoplay.foodmf.text.11": "  失明 III 00:15",
    "howtoplay.foodmf.text.12": "红葡萄酒",
    "howtoplay.foodmf.text.13": "  1/2:shank:",
    "howtoplay.foodmf.text.14": "  效率 III 00:20",
    "howtoplay.foodmf.text.15": "  反胃 II 00:15",
    "howtoplay.foodmf.text.16": "  失明 III 00:15",
    "howtoplay.foodmf.text.17": "白葡萄酒",
    "howtoplay.foodmf.text.18": "  1/2:shank:",
    "howtoplay.foodmf.text.19": "  效率 III 00:20",
    "howtoplay.foodmf.text.20": "  反胃 II 00:15",
    "howtoplay.foodmf.text.21": "  失明 III 00:15",
    "howtoplay.nutmf": "食品营养化",
    "howtoplay.nutmf.title": "Morefood更多食物 : 食品营养化",
    "howtoplay.nutmf.text.1": "有些食物有药水效果，下面是一些具有这些效果的食品",
    "howtoplay.nutmf.header.2": "食品营养化",
    "howtoplay.nutmf.text.2": ":shank::shank:",
    "item.morefood:black_candy": "黑色糖果",
    "item.morefood:blue_candy": "蓝色糖果",
    "item.morefood:brown_candy": "棕色糖果",
    "item.morefood:cyan_candy": "青色糖果",
    "item.morefood:gray_candy": "灰色糖果",
    "item.morefood:green_candy": "绿色糖果",
    "item.morefood:light_blue_candy": "浅蓝色糖果",
    "item.morefood:light_gray_candy": "浅灰色糖果",
    "item.morefood:lime_candy": "酸橙糖",
    "item.morefood:magenta_candy": "洋红糖果",
    "item.morefood:orange_candy": "橙色糖果",
    "item.morefood:pink_candy": "粉红糖果",
    "item.morefood:purple_candy": "紫色糖果",
    "item.morefood:red_candy": "红色糖果",
    "item.morefood:white_candy": "白色糖果",
    "item.morefood:yellow_candy": "黄色糖果",
    "item.morefood:candy_corn": "玉米糖",
    "item.morefood:candy_corn_bowl": "一碗玉米糖",
    "item.morefood:cooked_pumpkin_seeds": "熟南瓜子",
    "item.morefood:cooked_salted_pumpkin_seeds": "熟腌南瓜子",
    "item.morefood:empty_large_pumpkin_pale": "空的苍白大南瓜",
    "item.morefood:large_pumpkin_pale1": "大南瓜色",
    "item.morefood:large_pumpkin_pale2": "大南瓜色",
    "item.morefood:large_pumpkin_pale3": "大南瓜色",
    "item.morefood:large_pumpkin_pale4": "大南瓜色",
    "item.morefood:large_pumpkin_pale5": "饱满的苍白大南瓜",
    "item.morefood:empty_small_pumpkin_pale": "空的苍白小南瓜",
    "item.morefood:small_pumpkin_pale1": "苍白小南瓜",
    "item.morefood:small_pumpkin_pale2": "苍白小南瓜",
    "item.morefood:small_pumpkin_pale3": "饱满的苍白小南瓜",
    "item.morefood:ghast_cookie": "幽灵饼干",
    "tile.morefood:barley_crop.name": "§4无效块项",
    "tile.morefood:corn_crop.name": "§4无效块项",
    "tile.morefood:hops_crop.name": "§4无效块项",
    "tile.morefood:lettuce_crop.name": "§4无效块项",
    "tile.morefood:onion_crop.name": "§4无效块项",
    "tile.morefood:rice_crop.name": "§4无效块项",
    "tile.morefood:coffee_bush.name": "§4无效块项",
    "tile.morefood:gherkin_bush.name": "§4无效块项",
    "tile.morefood:grape_bush.name": "§4无效块项",
    "tile.morefood:pepper_bush.name": "§4无效块项",
    "tile.morefood:raspberry_bush.name": "§4无效块项",
    "tile.morefood:strawberry_bush.name": "§4无效块项",
    "tile.morefood:tea_bush.name": "§4无效块项",
    "tile.morefood:tomato_bush.name": "§4无效块项",
    "tile.morefood:vanilla_bush.name": "§4无效块项",
    "tile.morefood:lemon_sapling.name": "§4无效块项",
    "tile.morefood:olive_sapling.name": "§4无效块项",
    "tile.morefood:orange_sapling.name": "§4无效块项",
    "tile.morefood:plum_sapling.name": "§4无效块项",
    "tile.morefood:apple_sapling.name": "§4无效块项",
    "tile.morefood:banana_sapling.name": "§4无效块项",
    "tile.morefood:barley_block.name": "§4遗留无效块项",
    "tile.morefood:corn_block.name": "§4遗留无效块项",
    "tile.morefood:hops_block.name": "§4遗留无效块项",
    "tile.morefood:lettuce_block.name": "§4遗留无效块项",
    "tile.morefood:onion_block.name": "§4遗留无效块项",
    "tile.morefood:rice_block.name": "§4遗留无效块项",
    "tile.morefood:coffee_block.name": "§4遗留无效块项",
    "tile.morefood:gherkin_block.name": "§4遗留无效块项",
    "tile.morefood:grape_block.name": "§4遗留无效块项",
    "tile.morefood:pepper_block.name": "§4遗留无效块项",
    "tile.morefood:raspberry_block.name": "§4遗留无效块项",
    "tile.morefood:strawberry_block.name": "§4遗留无效块项",
    "tile.morefood:tea_block.name": "§4遗留无效块项",
    "tile.morefood:tomato_block.name": "§4遗留无效块项",
    "tile.morefood:vanilla_block.name": "§4遗留无效块项",
    "tile.morefood:bush_barley.name": "遗留的大麦灌木丛",
    "tile.morefood:bush_coffee.name": "遗留的咖啡灌木丛",
    "tile.morefood:bush_corn.name": "遗留的玉米灌木丛",
    "tile.morefood:bush_gherkin.name": "遗留的小黄瓜灌木丛",
    "tile.morefood:bush_grape.name": "遗留的葡萄灌木丛",
    "tile.morefood:bush_hops.name": "遗留的啤酒花灌木丛",
    "tile.morefood:bush_lettuce.name": "遗留的莴苣灌木丛",
    "tile.morefood:bush_onion.name": "遗留的洋葱灌木丛",
    "tile.morefood:bush_raspberry.name": "遗留的树莓灌木丛",
    "tile.morefood:bush_rice.name": "遗留的水稻灌木丛",
    "tile.morefood:bush_strawberry.name": "遗留的草莓灌木丛",
    "tile.morefood:bush_tea.name": "遗留的茶灌木丛",
    "tile.morefood:bush_tomato.name": "遗留的番茄灌木丛",
    "tile.morefood:bush_vanilla.name": "遗留的香草灌木丛",
    "tile.morefood:bush_pepper.name": "遗留的胡椒灌木丛",
    "tile.morefood:tree_apple.name": "遗留的苹果树叶",
    "tile.morefood:tree_banana.name": "遗留的香蕉树叶",
    "tile.morefood:tree_coconut.name": "遗留的椰子树叶",
    "tile.morefood:tree_lemon.name": "遗留的柠檬树叶",
    "tile.morefood:tree_olive.name": "遗留的橄榄树叶",
    "tile.morefood:tree_orange.name": "遗留的橙子树叶",
    "tile.morefood:tree_plum.name": "遗留的李子树叶"
}