{
  "type": "minecraft:crafting_shaped",
  "pattern": [
    "V S",
    "MEG",
    "FBT"
  ],
  "key": {
    "V": {
      "item": "morefood:vanilla_extract"
    },
    "S": {
      "item": "morefood:salt"
    },
    "M": {
      "item": "morefood:milk_carton"
    },
    "E": {
      "item": "minecraft:egg"
    },
    "G": {
      "item": "minecraft:sugar"
    },
    "F": {
      "item": "morefood:flour"
    },
    "B": {
      "item": "minecraft:bowl"
    },
    "T": {
      "item": "morefood:butter"
    }
  },
  "result": {
    "item": "morefood:icecream_cone",
    "count": 4
  }
}